pytactools-0.9.0.data/scripts/qinja
qinja/__init__.py
qinja/renderer.py
pytactools-0.9.0.dist-info/LICENSE
pytactools-0.9.0.dist-info/METADATA
pytactools-0.9.0.dist-info/WHEEL
pytactools-0.9.0.dist-info/top_level.txt
pytactools-0.9.0.dist-info/RECORD
